grlp/__init__.py
grlp/build_synthetic_network.py
grlp/grlp.py
GRLP-1.7.0.dist-info/LICENSE
GRLP-1.7.0.dist-info/METADATA
GRLP-1.7.0.dist-info/WHEEL
GRLP-1.7.0.dist-info/top_level.txt
GRLP-1.7.0.dist-info/RECORD
