Metadata-Version: 2.1
Name: GRLP
Version: 1.7.0
Summary: Evolves gravel-bed river long profiles
Home-page: https://github.com/awickert/GRLP
Author: Andrew D. Wickert
Author-email: awickert@umn.edu
License: UNKNOWN
Project-URL: Model page, https://csdms.colorado.edu/wiki/Model:GRLP
Keywords: fluvial geomorphology sediment transport landscape evolution
Platform: UNKNOWN
Classifier: Programming Language :: Python :: 2
Classifier: Programming Language :: Python :: 3
Classifier: License :: OSI Approved :: GNU General Public License v3 (GPLv3)
Classifier: Operating System :: OS Independent
Classifier: Topic :: Scientific/Engineering :: Hydrology
Classifier: Intended Audience :: Science/Research
Requires-Dist: matplotlib
Requires-Dist: numpy
Requires-Dist: scipy
